[{"metric": {"id": 2555418267795, "name": "Clusters Volumes", "system_name": "clusters_volumes", "unit": "volume"}, "period": {"name": null, "since": "2023-02-27T00:00:00Z", "until": "2023-03-05T23:59:59Z", "timezone": "Etc/UTC", "granularity": "day"}, "total": 0, "values": [0, 0, 0, 0, 0, 0, 0], "application": {"id": 1409622352571, "name": "IBM's App", "state": "live", "link": "/p/admin/applications/1409622352571", "description": "Default application created on signup.", "plan": {"id": 2357356350909, "name": "Standard News API Trial - Entities V3 (custom)"}, "account": {"id": 2445583898537, "name": "IBM", "link": "/buyers/accounts/2445583898537"}, "service": {"id": 2555417793963}}}, {"metric": {"id": 2555418267795, "name": "Clusters Volumes", "system_name": "clusters_volumes", "unit": "volume"}, "period": {"name": null, "since": "2023-02-27T00:00:00Z", "until": "2023-03-05T23:59:59Z", "timezone": "Etc/UTC", "granularity": "day"}, "total": 0, "values": [0, 0, 0, 0, 0, 0, 0], "application": {"id": 1409622565859, "name": "IBM Test and Dev Environment", "state": "live", "link": "/p/admin/applications/1409622565859", "description": "Second API key for IBM to be used to test new applications. ", "plan": {"id": 2357356369023, "name": "News API Standard (custom)"}, "account": {"id": 2445583898537, "name": "IBM", "link": "/buyers/accounts/2445583898537"}, "service": {"id": 2555417793963}}}, {"metric": {"id": 2555418267795, "name": "Clusters Volumes", "system_name": "clusters_volumes", "unit": "volume"}, "period": {"name": null, "since": "2023-02-27T00:00:00Z", "until": "2023-03-05T23:59:59Z", "timezone": "Etc/UTC", "granularity": "day"}, "total": 0, "values": [0, 0, 0, 0, 0, 0, 0], "application": {"id": 1409623052792, "name": "IBM ORI", "state": "live", "link": "/p/admin/applications/1409623052792", "description": "ORI API Key", "plan": {"id": 2357356410902, "name": "Standard Trial - 2023 (custom)"}, "account": {"id": 2445583898537, "name": "IBM", "link": "/buyers/accounts/2445583898537"}, "service": {"id": 2555417793963}}}, {"metric": {"id": 2555418267795, "name": "Clusters Volumes", "system_name": "clusters_volumes", "unit": "volume"}, "period": {"name": null, "since": "2023-02-27T00:00:00Z", "until": "2023-03-05T23:59:59Z", "timezone": "Etc/UTC", "granularity": "day"}, "total": 0, "values": [0, 0, 0, 0, 0, 0, 0], "application": {"id": 1409623052801, "name": "IBM Clarity", "state": "live", "link": "/p/admin/applications/1409623052801", "description": "Clarity API Key", "plan": {"id": 2357356410903, "name": "Standard Trial - 2023 (custom)"}, "account": {"id": 2445583898537, "name": "IBM", "link": "/buyers/accounts/2445583898537"}, "service": {"id": 2555417793963}}}, {"metric": {"id": 2555418267795, "name": "Clusters Volumes", "system_name": "clusters_volumes", "unit": "volume"}, "period": {"name": null, "since": "2023-02-27T00:00:00Z", "until": "2023-03-05T23:59:59Z", "timezone": "Etc/UTC", "granularity": "day"}, "total": 10544, "values": [144, 555, 1150, 938, 6698, 813, 246], "application": {"id": 1409623052817, "name": "IBM Market Insights", "state": "live", "link": "/p/admin/applications/1409623052817", "description": "Market Insights API Key", "plan": {"id": 2357356410904, "name": "Standard Trial - 2023 (custom)"}, "account": {"id": 2445583898537, "name": "IBM", "link": "/buyers/accounts/2445583898537"}, "service": {"id": 2555417793963}}}]